ximea/__init__.py
ximea/libs/32bit/xiArrOps32.dll
ximea/libs/32bit/xiapi32.dll
ximea/libs/64bit/xiArrOps64.dll
ximea/libs/64bit/xiapi64.dll
ximea/libs/x32/xiArrOps.so
ximea/libs/x64/xiArrOps.so
ximea/libs/xarm32/xiArrOps.so
ximea/libs/xarm64/xiArrOps.so
ximea/xi_wintypes.py
ximea/xiapi.py
ximea/xidefs.py
ximea_py-4.27.13.3.dist-info/METADATA
ximea_py-4.27.13.3.dist-info/WHEEL
ximea_py-4.27.13.3.dist-info/RECORD
